code_writer/__init__.py
code_writer/py.typed
test/__init__.py
test/test_basic.py
code_writer-1.3.0.dist-info/WHEEL
code_writer-1.3.0.dist-info/METADATA
code_writer-1.3.0.dist-info/licenses/LICENSE-MIT
code_writer-1.3.0.dist-info/RECORD
