Metadata-Version: 2.1
Name: code-writer
Version: 1.3.0
Summary: Default template for PDM package
License: MIT
Author-email: Ken Elkabany <ken@elkabany.com>
Requires-Python: >=3.8
Classifier: Programming Language :: Python :: 3
Classifier: Programming Language :: Python :: 3.10
Classifier: Programming Language :: Python :: 3.11
Classifier: Programming Language :: Python :: 3.12
Classifier: Programming Language :: Python :: 3.8
Classifier: Programming Language :: Python :: 3.9
Classifier: Topic :: Software Development :: Build Tools
